<?xml version="1.0" encoding="UTF-8"?>
<pg0:Programmes_DM xmlns:cd="http://www.amwa.tv/projects/rules/01/block/DM_ContentDetails/"
                     xmlns:pg0="http://www.amwa.tv/projects/rules/01/block/DM_Programmes/"
                     xmlns:pg1="http://www.amwa.tv/projects/rules/01/block/DM_Programmes_DomainSpecific/"
                     xmlns:id="http://www.amwa.tv/projects/rules/01/block/DM_Identification/"
                     xmlns:acs="http://www.amwa.tv/projects/rules/01/block/DM_InVisionAccessServices/">
    <id:Identifiers>
        <id:Identifier>
            <id:Identifier_Value>DRAZ855R/01</id:Identifier_Value>
            <id:Identifier_Type>Production Number</id:Identifier_Type>
            <id:Identifier_Authority>British Broadcasting Corporation</id:Identifier_Authority>
        </id:Identifier>
        <id:Identifier>
            <id:Identifier_Value>10.5240/XXXX-XXXX-XXXX-XXXX-XXXX-C</id:Identifier_Value>
            <id:Identifier_Type>EIDR</id:Identifier_Type>
        </id:Identifier>
    </id:Identifiers>
    <pg1:Programmes_DomainSpecific_DM>
        <pg1:Title_1>Series Title</pg1:Title_1>
        <pg1:Title_2>Programme Title - Post Watershed Version</pg1:Title_2>
        <pg1:Title_3>Test File</pg1:Title_3>
        <pg1:Synopsis>An example of a "new style" AS-11 file</pg1:Synopsis>
        <pg1:Genre>Test material</pg1:Genre>
        <pg1:Completion_Date>2015-11-13</pg1:Completion_Date>
        <pg1:Copyright_Year>2014</pg1:Copyright_Year>
        <pg1:Originator>BBC R&amp;D</pg1:Originator>
        <pg1:Distributor>Company XX</pg1:Distributor>
        <pg1:Contact_Email>a@example.com</pg1:Contact_Email>
        <pg1:Contact_Telephone_Number>01234567890</pg1:Contact_Telephone_Number>
        <pg1:Picture_Ratio>
            <pg1:Not_Full_Frame>
                <pg1:Custom_Picture>2.37:1 at top of frame</pg1:Custom_Picture>
            </pg1:Not_Full_Frame>
        </pg1:Picture_Ratio>
        <pg1:Product_Placement>true</pg1:Product_Placement>
        <pg1:Textless_Elements_Exist>false</pg1:Textless_Elements_Exist>
        <pg1:Programme_Has_Text>
            <pg1:Programme_Text_Language>en</pg1:Programme_Text_Language>
        </pg1:Programme_Has_Text>
        <pg1:Total_Programme_Duration>00:00:05:00</pg1:Total_Programme_Duration>
        <pg1:Line_Up_Start>09:59:30:00</pg1:Line_Up_Start>
        <pg1:Ident_Clock_Start>09:59:50:00</pg1:Ident_Clock_Start>
        <pg1:Is_Three_D>
            <pg1:ThreeD_Type>Side by side</pg1:ThreeD_Type>
        </pg1:Is_Three_D>
    </pg1:Programmes_DomainSpecific_DM>
    <acs:In_Vision_Access_Services>
        <acs:Open_Captions_Present>
            <acs:Caption_Language>en</acs:Caption_Language>
            <acs:Caption_Type>Hard of hearing</acs:Caption_Type>
        </acs:Open_Captions_Present>
        <acs:Signing_Present>
            <acs:Signing_Language>bfi</acs:Signing_Language>
            <acs:Signing_Type>Signer with programme</acs:Signing_Type>
        </acs:Signing_Present>
    </acs:In_Vision_Access_Services>
    <cd:Content_Details>
        <cd:PSE_Test_Results />
        <cd:Audio_Loudness_Details>
            <cd:Audio_Loudness_Specification>EBU R 128</cd:Audio_Loudness_Specification>
            <cd:Compliance_To_Specification_Is_Not_Achieved>
              <cd:Explanation>This programme is intentionally quiet as agreed when commissioned</cd:Explanation>
            </cd:Compliance_To_Specification_Is_Not_Achieved>
            <cd:Programme_Loudness_Value>-25.9</cd:Programme_Loudness_Value>
        </cd:Audio_Loudness_Details>
    </cd:Content_Details>
</pg0:Programmes_DM>
